easysql/__init__.py
easysql/easySQL.py
easysql/setting.py
easysql/type.py
easySQL_fiachia-3.2.8.dist-info/METADATA
easySQL_fiachia-3.2.8.dist-info/WHEEL
easySQL_fiachia-3.2.8.dist-info/licence.txt
easySQL_fiachia-3.2.8.dist-info/top_level.txt
easySQL_fiachia-3.2.8.dist-info/RECORD
