Metadata-Version: 2.1
Name: easySQL-fiachia
Version: 3.2.8
Summary: Easy SQL Used pymysql
Home-page: 
Author: fiachia
Author-email: 208473302@qq.com
Maintainer: fiachia
Maintainer-email: 208473302@qq.com
License: BSD License
Platform: all
License-File: licence.txt
Requires-Dist: pymysql
Requires-Dist: cryptography
